routekit_cli.py
routekit/__init__.py
routekit/config.py
routekit/helpers.py
routekit/qos/__init__.py
routekit/qos/classes.py
routekit/router/__init__.py
routekit/router/classes.py
routekit/router/core.py
routekit/router/util.py
routekit-0.2.2.dist-info/DESCRIPTION.rst
routekit-0.2.2.dist-info/METADATA
routekit-0.2.2.dist-info/RECORD
routekit-0.2.2.dist-info/WHEEL
routekit-0.2.2.dist-info/entry_points.txt
routekit-0.2.2.dist-info/metadata.json
routekit-0.2.2.dist-info/top_level.txt
